cyanure_gpu/__init__.py
cyanure_gpu/constants.py
cyanure_gpu/data_processing.py
cyanure_gpu/estimators.py
cyanure_gpu/logger.py
cyanure_gpu/erm/__init__.py
cyanure_gpu/erm/algebra.py
cyanure_gpu/erm/erm.py
cyanure_gpu/erm/multi_erm.py
cyanure_gpu/erm/simple_erm.py
cyanure_gpu/erm/param/__init__.py
cyanure_gpu/erm/param/model_param.py
cyanure_gpu/erm/param/problem_param.py
cyanure_gpu/losses/__init__.py
cyanure_gpu/losses/logistic.py
cyanure_gpu/losses/loss.py
cyanure_gpu/losses/loss_matrix.py
cyanure_gpu/losses/multi_class_logistic.py
cyanure_gpu/losses/square.py
cyanure_gpu/losses/square_multiclass.py
cyanure_gpu/losses/to_compile.py
cyanure_gpu/regularizers/__init__.py
cyanure_gpu/regularizers/lasso.py
cyanure_gpu/regularizers/none.py
cyanure_gpu/regularizers/regularizer.py
cyanure_gpu/regularizers/regularizer_matrix.py
cyanure_gpu/regularizers/ridge.py
cyanure_gpu/solvers/__init__.py
cyanure_gpu/solvers/accelerator.py
cyanure_gpu/solvers/ista.py
cyanure_gpu/solvers/solver.py
cyanure_gpu-1.0.2.dist-info/licenses/LICENSE
test/__init__.py
test/test_active_set.py
test/test_estimator.py
test/test_logistic_regression.py
cyanure_gpu-1.0.2.dist-info/METADATA
cyanure_gpu-1.0.2.dist-info/WHEEL
cyanure_gpu-1.0.2.dist-info/top_level.txt
cyanure_gpu-1.0.2.dist-info/RECORD
