Metadata-Version: 2.4
Name: cyanure_gpu
Version: 1.0.2
Summary: optimization toolbox for machine learning
Home-page: https://inria-thoth.github.io/cyanure_gpu/welcome.html
Author: Julien Mairal
Author-email: julien.mairal@inria.fr
License: bsd-3-clause
License-File: LICENSE
Requires-Dist: scikit-learn
Requires-Dist: torch<=2.5.1
Requires-Dist: numpy<=2.2.6
Dynamic: author
Dynamic: author-email
Dynamic: description
Dynamic: home-page
Dynamic: license
Dynamic: license-file
Dynamic: requires-dist
Dynamic: summary
